data/languages_names.eng.csv
data/languages_names.fra.csv
data/nationalities_names.eng.csv
data/nationalities_names.fra.csv
majormode/__init__.py
majormode/xebus/__init__.py
majormode/xebus/sis/__init__.py
majormode/xebus/sis/connector/__init__.py
majormode/xebus/sis/connector/eduka/__init__.py
xebus_sis_connector_eduka-1.1.18.dist-info/LICENSE.md
xebus_sis_connector_eduka-1.1.18.dist-info/METADATA
xebus_sis_connector_eduka-1.1.18.dist-info/WHEEL
xebus_sis_connector_eduka-1.1.18.dist-info/RECORD
