Metadata-Version: 2.1
Name: xebus-sis-connector-eduka
Version: 1.1.18
Summary: Connector to fetch data from a school's Eduka information system
Home-page: https://github.com/xebus/xebus-sis-connector-eduka
License: SEE LICENSE IN <LICENSE.md>
Keywords: connector,eduka,sis,xebus
Author: Daniel CAUNE
Author-email: daniel.caune@gmail.com
Requires-Python: >=3.10,<4.0
Classifier: Development Status :: 5 - Production/Stable
Classifier: License :: Other/Proprietary License
Classifier: Operating System :: OS Independent
Classifier: Programming Language :: Python
Classifier: Programming Language :: Python :: 3
Classifier: Programming Language :: Python :: 3.10
Classifier: Programming Language :: Python :: 3.11
Classifier: Topic :: Software Development :: Libraries
Requires-Dist: perseus-core-library (>=1.20.5,<2.0.0)
Requires-Dist: perseus-getenv-library (>=1.0.6,<2.0.0)
Requires-Dist: requests (>=2.32.3,<3.0.0)
Requires-Dist: unidecode (>=1.3.8,<2.0.0)
Requires-Dist: xebus-core-library (>=1.4.10,<2.0.0)
Requires-Dist: xebus-sis-connector-core-library (>=1.3.3,<2.0.0)
Project-URL: Repository, https://github.com/xebus/xebus-sis-connector-eduka
